pjer/__init__.py
pjer/main.py
pjer-0.0.10.dist-info/LICENSE
pjer-0.0.10.dist-info/METADATA
pjer-0.0.10.dist-info/WHEEL
pjer-0.0.10.dist-info/top_level.txt
pjer-0.0.10.dist-info/RECORD
