Metadata-Version: 2.1
Name: pjer
Version: 0.0.10
Summary: A python game engine
Home-page: https://github.com/lucasammer/pjer
Author: lucasammer
Author-email: me@lucasammer.com
License: UNKNOWN
Platform: UNKNOWN
Classifier: Programming Language :: Python :: 3
Classifier: License :: OSI Approved :: MIT License
Classifier: Operating System :: OS Independent
Requires-Python: >=3.6
